tofupilot/__init__.py
tofupilot/banner.py
tofupilot/error_tracking.py
tofupilot/openhtf/__init__.py
tofupilot/openhtf/tofupilot.py
tofupilot/openhtf/upload.py
tofupilot/pytest/__init__.py
tofupilot/pytest/plugin.py
tofupilot/pytest/pytest.ini
tofupilot/telemetry_config.py
tofupilot/v1/__init__.py
tofupilot/v1/client.py
tofupilot/v1/constants/__init__.py
tofupilot/v1/constants/attachments.py
tofupilot/v1/constants/requests.py
tofupilot/v1/models/__init__.py
tofupilot/v1/models/models.py
tofupilot/v1/pyproject.toml
tofupilot/v1/responses/__init__.py
tofupilot/v1/responses/responses.py
tofupilot/v1/utils/__init__.py
tofupilot/v1/utils/dates.py
tofupilot/v1/utils/files.py
tofupilot/v1/utils/logger.py
tofupilot/v1/utils/network.py
tofupilot/v2/__init__.py
tofupilot/v2/_hooks/__init__.py
tofupilot/v2/_hooks/example_hook.py
tofupilot/v2/_hooks/sdkhooks.py
tofupilot/v2/_hooks/types.py
tofupilot/v2/_version.py
tofupilot/v2/attachments.py
tofupilot/v2/basesdk.py
tofupilot/v2/batches.py
tofupilot/v2/client_with_error_tracking.py
tofupilot/v2/errors/__init__.py
tofupilot/v2/errors/apierror.py
tofupilot/v2/errors/error_bad_gateway.py
tofupilot/v2/errors/error_bad_request.py
tofupilot/v2/errors/error_conflict.py
tofupilot/v2/errors/error_forbidden.py
tofupilot/v2/errors/error_internal_server_error.py
tofupilot/v2/errors/error_not_found.py
tofupilot/v2/errors/error_unprocessable_content.py
tofupilot/v2/httpclient.py
tofupilot/v2/models/__init__.py
tofupilot/v2/models/attachment_initializeop.py
tofupilot/v2/models/batch_createop.py
tofupilot/v2/models/batch_deleteop.py
tofupilot/v2/models/batch_getop.py
tofupilot/v2/models/batch_listop.py
tofupilot/v2/models/batch_updateop.py
tofupilot/v2/models/error_bad_gateway.py
tofupilot/v2/models/error_bad_request.py
tofupilot/v2/models/error_conflict.py
tofupilot/v2/models/error_forbidden.py
tofupilot/v2/models/error_internal_server_error.py
tofupilot/v2/models/error_not_found.py
tofupilot/v2/models/error_unprocessable_content.py
tofupilot-1.12.1.dist-info/LICENSE
tofupilot-1.12.1.dist-info/METADATA
tofupilot-1.12.1.dist-info/WHEEL
tofupilot-1.12.1.dist-info/RECORD
