Metadata-Version: 2.3
Name: tofupilot
Version: 1.12.1
Summary: Official Python client for TofuPilot with OpenHTF integration, real-time streaming and file attachment support
License: MIT
Keywords: automatic,hardware,testing,tofupilot,openhtf,sdk
Author: TofuPilot Team
Author-email: hello@tofupilot.com
Requires-Python: >=3.9.2
Classifier: Programming Language :: Python :: 3
Classifier: Operating System :: OS Independent
Classifier: Development Status :: 5 - Production/Stable
Classifier: Intended Audience :: Developers
Classifier: Intended Audience :: Manufacturing
Classifier: Topic :: Scientific/Engineering
Classifier: Topic :: Software Development :: Testing
Classifier: Topic :: Software Development :: Libraries :: Python Modules
Provides-Extra: dev
Requires-Dist: build ; extra == "dev"
Requires-Dist: certifi (>=2023.7.22)
Requires-Dist: httpcore (>=1.0.9)
Requires-Dist: httpx (>=0.28.1)
Requires-Dist: mypy (==1.15.0) ; extra == "dev"
Requires-Dist: openhtf
Requires-Dist: packaging (>=20.0)
Requires-Dist: paho-mqtt (>=2.0.0)
Requires-Dist: posthog (>=3.0.0)
Requires-Dist: pydantic (>=2.11.2)
Requires-Dist: pylint (==3.2.3) ; extra == "dev"
Requires-Dist: pytest (>=6.0.0)
Requires-Dist: python-dotenv ; extra == "dev"
Requires-Dist: requests (>=2.25.0)
Requires-Dist: setuptools (>=50.0.0) ; extra == "dev"
Requires-Dist: trycast ; extra == "dev"
Requires-Dist: twine ; extra == "dev"
Project-URL: Documentation, https://tofupilot.com/docs
Project-URL: Homepage, https://github.com/tofupilot/python-client
Project-URL: Issues, https://github.com/tofupilot/python-client/issues
Project-URL: Repository, https://github.com/tofupilot/python-client
